MANIFEST.in
README.txt
setup.cfg
setup.py
XStatic_jReject.egg-info/PKG-INFO
XStatic_jReject.egg-info/SOURCES.txt
XStatic_jReject.egg-info/dependency_links.txt
XStatic_jReject.egg-info/namespace_packages.txt
XStatic_jReject.egg-info/not-zip-safe
XStatic_jReject.egg-info/top_level.txt
xstatic/__init__.py
xstatic/pkg/__init__.py
xstatic/pkg/jreject/__init__.py
xstatic/pkg/jreject/data/css/jquery.reject.css
xstatic/pkg/jreject/data/img/browser_chrome.gif
xstatic/pkg/jreject/data/img/browser_firefox.gif
xstatic/pkg/jreject/data/img/browser_gcf.gif
xstatic/pkg/jreject/data/img/browser_konqueror.gif
xstatic/pkg/jreject/data/img/browser_msie.gif
xstatic/pkg/jreject/data/img/browser_opera.gif
xstatic/pkg/jreject/data/img/browser_safari.gif
xstatic/pkg/jreject/data/js/jquery.jreject.js