Metadata-Version: 1.0
Name: XStatic-jReject
Version: 1.1.0.1
Summary: jReject 1.1.0 (XStatic packaging standard)
Home-page: http://jreject.turnwheel.com/
Author: Nikunj Aggarwal
Author-email: nikunj2512@gmail.com
License: (same as jReject)
Keywords: jreject xstatic
Platform: any
